{
	"mMetal": {
		"albedo": "traincouchmetal_alb.png",
		"mix": "traincouchmetal_mix.png",
		"normal": "traincouchmetal_nrm.png"
	},
	"mSeat": {
		"albedo": "traincouchseat_alb.png",
		"mix": "traincouchseat_mix.png",
		"normal": "traincouchseat_nrm.png"
	},
	"mPosters": {
		"albedo": "trainposters_alb.png"
	},
	"mWall": {
		"albedo": "trainwall_alb.png",
		"mix": "trainwall_mix.png",
		"normal": "trainwall_nrm.png"
	},
	"mFloor": {
		"albedo": "trainfloor_alb.png",
		"mix": "trainfloor_mix.png",
		"normal": "trainfloor_nrm.png"
	},
	"mLights": {
		"shader": "warm_unlit"
	},
	"mGlass": {
		"albedo": "trainwoods_alb.png",
		"shader": "fast_horiz"
	}
}
